{
  "os": "Windows-10-10.0.26100-SP0",
  "python": "CPython 3.11.9",
  "startedAt": "2025-06-13T10:04:47.708491Z",
  "program": "c:\\Users\\jonas\\PycharmProjects\\ducks-riding-lamas\\main.py",
  "codePath": "main.py",
  "git": {
    "remote": "https://github.com/fivecodingfive/ducks-riding-lamas.git",
    "commit": "0fd59ccbf80b5344c0e10e35962fd5c0c325350f"
  },
  "email": "jonas05.coding@gmail.com",
  "root": "./wandb",
  "host": "JCL",
  "executable": "C:\\Users\\jonas\\PycharmProjects\\ducks-riding-lamas\\venv\\Scripts\\python.exe",
  "codePathLocal": "main.py",
  "cpu_count": 4,
  "cpu_count_logical": 8,
  "disk": {
    "/": {
      "total": "510674333696",
      "used": "299214692352"
    }
  },
  "memory": {
    "total": "16969424896"
  },
  "cpu": {
    "count": 4,
    "countLogical": 8
  }
}